toolwrap_lite/__init__.py
toolwrap_lite/decorators.py
toolwrap_lite/registry.py
toolwrap_lite/schema.py
toolwrap_lite/utils.py
toolwrap_lite-0.3.0.dist-info/licenses/LICENSE
toolwrap_lite-0.3.0.dist-info/METADATA
toolwrap_lite-0.3.0.dist-info/WHEEL
toolwrap_lite-0.3.0.dist-info/top_level.txt
toolwrap_lite-0.3.0.dist-info/RECORD
