Metadata-Version: 2.4
Name: toolwrap-lite
Version: 0.3.0
Summary: Auto-generate OpenAI-compatible tool schemas from Python functions using decorators.
Author: Gagan Naidu
Author-email: Gagan Naidu <gagan.globin76@gmail.com>
License: MIT
Project-URL: Homepage, https://github.com/gagannaidu/toolwrap-lite
Project-URL: Documentation, https://github.com/gagannaidu/toolwrap-lite
Project-URL: Source, https://github.com/gagannaidu/toolwrap-lite
Project-URL: Issues, https://github.com/gagannaidu/toolwrap-lite/issues
Keywords: OpenAI,tool schema,AI agents,JSON schema,decorator,Python,LangChain,CrewAI
Classifier: Programming Language :: Python :: 3
Classifier: License :: OSI Approved :: MIT License
Classifier: Operating System :: OS Independent
Classifier: Development Status :: 3 - Alpha
Classifier: Intended Audience :: Developers
Classifier: Topic :: Software Development :: Libraries
Requires-Python: >=3.7
License-File: LICENSE
Dynamic: author
Dynamic: license-file
